<xml
	xmlns="http://www.w3.org/1999/xhtml">
	<variables>
		<variable type="" id="`jEk@4|i[#Fk?(8x)AV.-my variable" islocal="false" iscloud="false">my variable</variable>
	</variables>
	<block
                id=".mBK=X;NxZ51=+`3)Il."
                type="musiccreation_playNote"
                x="75" y="156"
            >
		<value name="NOTE">
			<shadow
                id="C3,ytHvwhMdp!l+z$tPt"
                type="note"
                
            >
				<field name="NOTE">60</field>
			</shadow>
		</value>
		<value name="SECS">
			<shadow
                id="4pvN(sC_x$HD%OON;X[2"
                type="musiccreation_menu_BEATS"
                
            >
				<field name="BEATS">0.25</field>
			</shadow>
		</value>
		<next>
			<block
                id="yi=z+]6N0kBVh7.(mbL3"
                type="musiccreation_playNote"
                
            >
				<value name="NOTE">
					<shadow
                id="yC=!n1ek5,)0iVN~4*d:"
                type="note"
                
            >
						<field name="NOTE">60</field>
					</shadow>
				</value>
				<value name="SECS">
					<shadow
                id="*mlW=C[RhO~^dTJwiTS="
                type="musiccreation_menu_BEATS"
                
            >
						<field name="BEATS">0.75</field>
					</shadow>
				</value>
				<next>
					<block
                id="J~oHJ5ADg[Q0V}2%lcQI"
                type="musiccreation_playNote"
                
            >
						<value name="NOTE">
							<shadow
                id="q[Cuyy#/4sUCLZPOuD-6"
                type="note"
                
            >
								<field name="NOTE">60</field>
							</shadow>
						</value>
						<value name="SECS">
							<shadow
                id="KQk%$JK8Q/5^1%Kd)`V."
                type="musiccreation_menu_BEATS"
                
            >
								<field name="BEATS">0.25</field>
							</shadow>
						</value>
					</block>
				</next>
			</block>
		</next>
	</block>
</xml>